setup.py
blockstack_gpg/__init__.py
blockstack_gpg/gpg.py
blockstack_gpg/version.py
blockstack_gpg.egg-info/PKG-INFO
blockstack_gpg.egg-info/SOURCES.txt
blockstack_gpg.egg-info/dependency_links.txt
blockstack_gpg.egg-info/not-zip-safe
blockstack_gpg.egg-info/requires.txt
blockstack_gpg.egg-info/top_level.txt