Metadata-Version: 1.1
Name: blockstack-gpg
Version: 0.14.0
Summary: GPG integration for Blockstack client applications
Home-page: https://github.com/blockstack/blockstack-gpg
Author: Blockstack.org
Author-email: support@blockstack.org
License: GPLv3
Download-URL: https://github.com/blockstack/gitsec/archive/master.zip
Keywords: blockchain git crypography name key value store data
Platform: UNKNOWN
Classifier: Intended Audience :: Developers
Classifier: License :: OSI Approved :: GNU General Public License v3 (GPLv3)
Classifier: Operating System :: OS Independent
Classifier: Programming Language :: Python
Classifier: Topic :: Internet
Classifier: Topic :: Security :: Cryptography
Classifier: Topic :: Software Development :: Libraries :: Python Modules
